<?xml version="1.0" encoding="iso-8859-1"?>
<mosinstall type="template" version="1.0.x">
	<name>ja_acrus</name>
	<creationDate>02 Oct 06</creationDate>
	<author>JoomlArt.com</author>
	<copyright></copyright>
	<authorEmail>webmaster@joomlart.com</authorEmail>
	<authorUrl>http://www.joomlart.com</authorUrl>
	<version>1.0</version>
	<description></description>
	<files>
		<filename>index.html</filename>
		<filename>index.php</filename>
		<filename>templateDetails.xml</filename>
	</files>
	<images>
		<filename>images/arrow.png</filename>
		<filename>images/but-bg.gif</filename>
		<filename>images/but-css.gif</filename>
		<filename>images/but-xhtml.gif</filename>
		<filename>images/emailButton.png</filename>
		<filename>images/image-09-2.jpg</filename>
		<filename>images/image-09.jpg</filename>
		<filename>images/information.png</filename>
		<filename>images/ja-button.gif</filename>
		<filename>images/ja-contentable-bg.gif</filename>
		<filename>images/ja-footer-center.gif</filename>
		<filename>images/ja-footer-left.gif</filename>
		<filename>images/ja-footer-right.gif</filename>
		<filename>images/ja-logo-01.jpg</filename>
		<filename>images/ja-moduletable-a-hover.gif</filename>
		<filename>images/ja-moduletable-a.gif</filename>
		<filename>images/ja-moduletable-bar.gif</filename>
		<filename>images/ja-moduletable-bg.gif</filename>
		<filename>images/ja-moduletable-bottom.gif</filename>
		<filename>images/ja-moduletable-center.gif</filename>
		<filename>images/ja-moduletable-top.gif</filename>
		<filename>images/ja-pathway-bg.gif</filename>
		<filename>images/ja-readon-bg.gif</filename>
		<filename>images/ja-search-bg.gif</filename>
		<filename>images/ja-topnav-center.gif</filename>
		<filename>images/ja-topnav-left.gif</filename>
		<filename>images/ja-topnav-right.gif</filename>
		<filename>images/news-bottom.gif</filename>
		<filename>images/news-bottom2.gif</filename>
		<filename>images/news-center.gif</filename>
		<filename>images/news-center2.gif</filename>
		<filename>images/news-top.gif</filename>
		<filename>images/news-top2.gif</filename>
		<filename>images/pdf_button.png</filename>
		<filename>images/printButton.png</filename>
		<filename>images/search.gif</filename>
		<filename>images/seperator.gif</filename>
		<filename>template_thumbnail.png</filename>
	</images>
	<css>
		<filename>css/template_css.css</filename>
	</css>
</mosinstall>